RobotFrameworkBasic/__init__.py
RobotFrameworkBasic/decorator.py
RobotFrameworkBasic/error.py
RobotFrameworkBasic/version.py
RobotFrameworkBasic/action/__init__.py
RobotFrameworkBasic/action/assertion.py
RobotFrameworkBasic/action/assertion.pyi
RobotFrameworkBasic/action/calculate.py
RobotFrameworkBasic/action/calculate.pyi
RobotFrameworkBasic/action/config.py
RobotFrameworkBasic/basic/__init__.py
RobotFrameworkBasic/basic/common.py
movoid_robotframework-1.8.3.dist-info/METADATA
movoid_robotframework-1.8.3.dist-info/WHEEL
movoid_robotframework-1.8.3.dist-info/top_level.txt
movoid_robotframework-1.8.3.dist-info/RECORD
