Metadata-Version: 2.4
Name: movoid_robotframework
Version: 1.8.3
Home-page: 
Author: movoid
Author-email: bobrobotsun@163.com
Requires-Dist: robotframework<8,>=6.0
Requires-Dist: movoid_config>=1.2.5
Requires-Dist: movoid_debug>=1.4.10
Requires-Dist: movoid_function>=1.8.5
Requires-Dist: movoid_log>=1.2.4
Dynamic: author
Dynamic: author-email
Dynamic: description
Dynamic: description-content-type
Dynamic: requires-dist
